{
  "iss": "https://accounts.google.com",
  "sub": "109172005615349494371",
  "name": "Sumit Kumar Dandia",
  "email": "sumitkkumar639@gmail.com",
  "picture": "https://lh3.googleusercontent.com/a/ACg8ocJDdtXVwjmFB5X95A0DQM7gmbJFGI7Gwzqw-fj8KifQDM4=s96-c",
  "full_name": "Sumit Kumar Dandia",
  "user_name": "sumit639-code",
  "avatar_url": "https://lh3.googleusercontent.com/a/ACg8ocJDdtXVwjmFB5X95A0DQM7gmbJFGI7Gwzqw-fj8KifQDM4=s96-c",
  "provider_id": "109172005615349494371",
  "email_verified": true,
  "phone_verified": false,
  "preferred_username": "sumit639-code"
}
